cobs/__init__.py
cobs/_version/__init__.py
cobs/cobs/__init__.py
cobs/cobs/_cobs_ext.cp311-win_amd64.pyd
cobs/cobs/_cobs_py.py
cobs/cobs/test.py
cobs/cobsr/__init__.py
cobs/cobsr/_cobsr_ext.cp311-win_amd64.pyd
cobs/cobsr/_cobsr_py.py
cobs/cobsr/test.py
cobs-1.2.1.dist-info/LICENSE.txt
cobs-1.2.1.dist-info/METADATA
cobs-1.2.1.dist-info/WHEEL
cobs-1.2.1.dist-info/top_level.txt
cobs-1.2.1.dist-info/RECORD
