Metadata-Version: 2.1
Name: cobs
Version: 1.2.1
Summary: Consistent Overhead Byte Stuffing (COBS)
Author-email: Craig McQueen <python@craig.mcqueen.id.au>
License: ----------------------------------------------------------------------------
Project-URL: Homepage, https://github.com/cmcqueen/cobs-python
Project-URL: Bug Tracker, https://github.com/cmcqueen/cobs-python/issues
Keywords: byte stuffing
Classifier: Development Status :: 5 - Production/Stable
Classifier: Intended Audience :: Developers
Classifier: License :: OSI Approved :: MIT License
Classifier: Programming Language :: Python :: 3
Classifier: Topic :: Communications
Requires-Python: >=3.6
License-File: LICENSE.txt
